swifter/__init__.py
swifter/base.py
swifter/parallel_accessor.py
swifter/swifter.py
swifter/swifter_tests.py
swifter/tqdm_dask_progressbar.py
swifter-1.0.9.dist-info/LICENSE
swifter-1.0.9.dist-info/METADATA
swifter-1.0.9.dist-info/WHEEL
swifter-1.0.9.dist-info/top_level.txt
swifter-1.0.9.dist-info/RECORD
