Metadata-Version: 2.1
Name: swifter
Version: 1.0.9
Summary: A package which efficiently applies any function to a pandas dataframe or series in the fastest available manner
Home-page: https://github.com/jmcarpenter2/swifter
Author: Jason Carpenter
Author-email: jcarpenter@manifold.ai
License: UNKNOWN
Download-URL: https://github.com/jmcarpenter2/swifter/archive/1.0.9.tar.gz
Keywords: pandas,dask,apply,function,parallelize,vectorize
Platform: UNKNOWN
License-File: LICENSE
Requires-Dist: pandas (>=1.0.0)
Requires-Dist: psutil (>=5.6.6)
Requires-Dist: dask[dataframe] (>=2.10.0)
Requires-Dist: tqdm (>=4.33.0)
Requires-Dist: ipywidgets (>=7.0.0)
Requires-Dist: cloudpickle (>=0.2.2)
Requires-Dist: parso (>0.4.0)
Requires-Dist: bleach (>=3.1.1)
Provides-Extra: modin-dask
Requires-Dist: modin[dask] (>=0.8.1.1) ; extra == 'modin-dask'
Provides-Extra: modin-ray
Requires-Dist: modin[ray] (>=0.8.1.1) ; extra == 'modin-ray'
